bikinibottom/__init__.py
bikinibottom/core.py
bikinibottom-0.9.0.dist-info/METADATA
bikinibottom-0.9.0.dist-info/WHEEL
bikinibottom-0.9.0.dist-info/top_level.txt
bikinibottom-0.9.0.dist-info/RECORD
